robosource_common/__init__.py
robosource_common/coachbot.py
robosource_common/file_blob.py
robosource_common/file_share.py
robosource_common-20241030.1.dist-info/METADATA
robosource_common-20241030.1.dist-info/WHEEL
robosource_common-20241030.1.dist-info/licenses/LICENSE
robosource_common-20241030.1.dist-info/RECORD
